{
  "stamp": 1777626743007,
  "photos": [
    {
      "name": "Minh Tr?, ??o ??t t?i th?p Nh? ? 3-2026.png",
      "url": "https://drive.google.com/thumbnail?id=1du-tHjs1ia6vdxc0z1i9l1dYwuJMbmNo&sz=w1200"
    },
    {
      "name": "Tu? Minh t?i th?p Nh? ? 17-3-2026 2.png",
      "url": "https://drive.google.com/thumbnail?id=1CT-IVJ_C5MROaRIr5zoUsrXAxi2oow4B&sz=w1200"
    },
    {
      "name": "Tu? Minh t?i th?p Nh? ? 17-3-2026.png",
      "url": "https://drive.google.com/thumbnail?id=1_rraWsaizf6kKLZvNaI5pHRfTbLxvI53&sz=w1200"
    },
    {
      "name": "Tu? Minh, ??o ??t t?i th?p Nh? ? Nepal 17-3-2026.png",
      "url": "https://drive.google.com/thumbnail?id=1DCPQ39p9SoMeHpi_7ZL18lTyQ0oxhFr9&sz=w1200"
    }
  ]
}